easy_rag_pipeline/__init__.py
easy_rag_pipeline/api.py
easy_rag_pipeline/config.py
easy_rag_pipeline/embed.py
easy_rag_pipeline/generate.py
easy_rag_pipeline/ingest.py
easy_rag_pipeline/pipeline.py
easy_rag_pipeline/retrieve.py
easy_rag_pipeline/store.py
easy_rag_pipeline/utils.py
easy_rag_pipeline-0.1.5.dist-info/licenses/LICENSE
easy_rag_pipeline-0.1.5.dist-info/METADATA
easy_rag_pipeline-0.1.5.dist-info/WHEEL
easy_rag_pipeline-0.1.5.dist-info/top_level.txt
easy_rag_pipeline-0.1.5.dist-info/RECORD
