Metadata-Version: 2.4
Name: easy_rag_pipeline
Version: 0.1.5
Summary: A reusable and configurable RAG (Retrieval-Augmented Generation) pipeline.
Author: Engr.Hamza
License-File: LICENSE
Requires-Dist: langchain
Requires-Dist: langchain-core
Requires-Dist: langchain-openai
Requires-Dist: langchain-community
Requires-Dist: langchain-groq
Requires-Dist: langchain-google-genai
Requires-Dist: faiss-cpu
Requires-Dist: pypdf
Requires-Dist: tiktoken
Requires-Dist: sentence-transformers
Requires-Dist: pyyaml
Requires-Dist: python-dotenv
Requires-Dist: streamlit
Dynamic: author
Dynamic: description
Dynamic: description-content-type
Dynamic: license-file
Dynamic: requires-dist
Dynamic: summary
